[{"id": 1, "first_name": "Cindy 2", "last_name": "Tan 2 ", "email": "cindytan@somewhere.com2", "send_marketing_material": null}, {"id": 2, "first_name": "John", "last_name": "Doe", "email": "johndoe@somewhere.com", "send_marketing_material": true}, {"id": 3, "first_name": "Ethan", "last_name": "Wong", "email": "ethanwong@somewhere.com", "send_marketing_material": true}, {"id": 394919, "first_name": "Gabriel", "last_name": "Seet", "email": "test@gmail.com", "send_marketing_material": true}, {"id": 601399, "first_name": "Melody", "last_name": "Heng", "email": "mel@pampascollective.com", "send_marketing_material": true}]